mcp_server_live_furloop/__init__.py
mcp_server_live_furloop/server.py
mcp_server_consignspace-0.1.2.dist-info/METADATA
mcp_server_consignspace-0.1.2.dist-info/WHEEL
mcp_server_consignspace-0.1.2.dist-info/entry_points.txt
mcp_server_consignspace-0.1.2.dist-info/licenses/LICENSE
mcp_server_consignspace-0.1.2.dist-info/RECORD
