Metadata-Version: 2.4
Name: mcp-server-consignspace
Version: 0.1.2
Summary: ConsignSpace MCP server for Claude Desktop - manage cart and orders
Project-URL: Homepage, https://github.com/EvanGan2023/mcp-server-consignspace
Project-URL: Repository, https://github.com/EvanGan2023/mcp-server-consignspace
Project-URL: Issues, https://github.com/EvanGan2023/mcp-server-consignspace/issues
Author-email: EvanGan2023 <134857100+EvanGan2023@users.noreply.github.com>
License: MIT
License-File: LICENSE
Keywords: ai,cart,claude,consignspace,mcp,orders,reseller
Classifier: Development Status :: 4 - Beta
Classifier: Intended Audience :: Developers
Classifier: License :: OSI Approved :: MIT License
Classifier: Operating System :: OS Independent
Classifier: Programming Language :: Python :: 3
Classifier: Programming Language :: Python :: 3.8
Classifier: Programming Language :: Python :: 3.9
Classifier: Programming Language :: Python :: 3.10
Classifier: Programming Language :: Python :: 3.11
Classifier: Programming Language :: Python :: 3.12
Classifier: Programming Language :: Python :: 3.13
Classifier: Topic :: Software Development :: Libraries :: Python Modules
Requires-Python: >=3.8
Requires-Dist: aiohttp>=3.8.0
Requires-Dist: mcp>=1.11.0
